{ "databaseChangeLog": [
    {
        "changeSet": {
          "id": "UCSBOrganization-1",
          "author": "ryanlonacre",
          "preConditions": [
            {
              "onFail": "MARK_RAN"
            },
            {
              "not": [
                {
                  "tableExists": {
                    "tableName": "ucsborganizations"
                  }
                }
              ]
            }
          ],
          "changes": [
            {
              "createTable": {
                "columns": [
                  {
                    "column": {
                      "constraints": {
                        "primaryKey": true,
                        "primaryKeyName": "UCSBORGANIZATION_PK"
                      },
                      "name": "org_code",
                      "type": "VARCHAR(255)"
                    }
                  },
                  {
                    "column": {
                      "constraints": {
                        "nullable": false
                      },
                      "name": "org_translation_short",
                      "type": "VARCHAR(255)"
                    }
                  },
                  {
                    "column": {
                      "constraints": {
                        "nullable": false
                      },
                      "name": "org_translation",
                      "type": "VARCHAR(255)"
                    }
                  },
                  {
                    "column": {
                      "constraints": {
                        "nullable": false
                      },
                      "name": "inactive",
                      "type": "BOOLEAN"
                    }
                  }],
                "tableName": "ucsborganizations"
              }
            }]
        }
    }
]}